README.rst
pkcs7csr.py
setup.py
pkcs7csr.egg-info/PKG-INFO
pkcs7csr.egg-info/SOURCES.txt
pkcs7csr.egg-info/dependency_links.txt
pkcs7csr.egg-info/requires.txt
pkcs7csr.egg-info/top_level.txt