Metadata-Version: 1.1
Name: pkcs7csr
Version: 1.0.1
Summary: A Python module for creating Microsoft style "PKCS #7 renewal requests"
Home-page: https://github.com/magnuswatn/pkcs7csr
Author: Magnus Watn
Author-email: UNKNOWN
License: MIT
Keywords: ad adcs certsrv pki certificate csr iis renewal
Platform: UNKNOWN
Classifier: Development Status :: 4 - Beta
Classifier: Intended Audience :: System Administrators
Classifier: Intended Audience :: Developers
Classifier: License :: OSI Approved :: MIT License
Classifier: Operating System :: POSIX :: Linux
Classifier: Programming Language :: Python :: 2
Classifier: Programming Language :: Python :: 2.7
Classifier: Programming Language :: Python :: 3
Classifier: Programming Language :: Python :: 3.4
Classifier: Programming Language :: Python :: 3.5
Classifier: Programming Language :: Python :: 3.6
Classifier: Topic :: Internet :: WWW/HTTP
Classifier: Topic :: Security
Classifier: Topic :: Software Development :: Libraries
Classifier: Topic :: System :: Systems Administration
